MANIFEST.in
pip-requirements-min-django.txt
pip-requirements-test.txt
pip-requirements.txt
setup.py
django_python_code_field.egg-info/PKG-INFO
django_python_code_field.egg-info/SOURCES.txt
django_python_code_field.egg-info/dependency_links.txt
django_python_code_field.egg-info/not-zip-safe
django_python_code_field.egg-info/requires.txt
django_python_code_field.egg-info/top_level.txt
python_field/__init__.py
python_field/fields.py
python_field/tests/__init__.py
python_field/tests/manage.py
python_field/tests/models.py
python_field/tests/settings.py
python_field/tests/tests.py
python_field/tests/urls.py
python_field/tests/views.py
python_field/tests/management/__init__.py
python_field/tests/management/commands/__init__.py