Metadata-Version: 1.1
Name: django-python-code-field
Version: 1.0.0
Summary: Store python source code (syntax checked) in database.
Home-page: https://github.com/chrisspen/django-python-code-field/
Author: Chris Spencer
Author-email: chrisspen@gmail.com
License: UNKNOWN
Platform: UNKNOWN
Classifier: Programming Language :: Python
Classifier: License :: OSI Approved :: BSD License
Classifier: Operating System :: OS Independent
Classifier: Framework :: Django
Classifier: Programming Language :: Python :: 2.7
Classifier: Environment :: Web Environment
